{
  "kind": "collectionType",
  "collectionName": "contents",
  "info": {
    "name": "content",
    "description": ""
  },
  "options": {
    "increments": true,
    "timestamps": true,
    "draftAndPublish": true
  },
  "pluginOptions": {},
  "attributes": {
    "name": {
      "type": "string"
    },
    "slug": {
      "type": "uid",
      "targetField": "name"
    },
    "subtitle": {
      "type": "text"
    },
    "post": {
      "model": "file",
      "via": "related",
      "allowedTypes": [
        "images",
        "videos"
      ],
      "plugin": "upload",
      "required": true,
      "pluginOptions": {}
    },
    "type": {
      "model": "type"
    },
    "admin_user": {
      "plugin": "admin",
      "model": "user"
    }
  }
}
